{
  "title": "1970-08-30 Freshwater",
  "metadata": {
    "date": "1970-08-30",
    "location": {
      "city": "Freshwater",
      "country": "United Kingdom",
      "venue": "Afton Down"
    }
  },
  "content": {
    "content": [
      {
        "kind": "prologue",
        "reference": "song.suzanne",
        "content": {
          "text": [
            "Oh It's good to be here alone in front of six hundred thousand people. It's a large nation but it's still weak, still very weak. It needs to get a lot stronger before it can claim a right to a land"
          ]
        }
      },
      {
        "kind": "variation",
        "reference": "song.tonight_will_be_fine",
        "content": {
          "text": [
            [
              "(sung as additional verses)",
              " I've looked into the mirrors in numberless places",
              " They all smile back at me with the most troublesome faces.",
              " The cards that they dealt me, no there weren't any aces",
              " And the horses just don't listen to me at the races."
            ],
            [
              " There's still one or two of us, walking the street",
              " No arrows of direction painted under our feet",
              " No angels to warn us away from the heat",
              " And no honey to keep us where it is sweet"
            ]
          ]
        }
      }
    ]
  },
  "kind": "live",
  "annotations": [
    {
      "anchor": "s2.p2.l4",
      "annotations": [
        {
          "user": "symbols bot",
          "content": [
            {
              "kind": "docref",
              "docRef": "symbol.sweetness"
            }
          ],
          "id": "1"
        }
      ],
      "newAnchor": "2:9"
    }
  ],
  "user": "sudonhim",
  "version": 0,
  "newContent": {
    "sectionalContent": [
      {
        "id": "prologue_to_suzanne",
        "title": {
          "kind": "text",
          "tokens": [
            {
              "kind": "text",
              "text": "Prologue to "
            },
            {
              "kind": "reference",
              "reference": {
                "kind": "document",
                "documentId": "song.suzanne"
              }
            }
          ]
        },
        "fragments": [
          {
            "kind": "text",
            "id": "1",
            "tokens": [
              {
                "kind": "text",
                "text": "Oh It's good to be here alone in front of six hundred thousand people. It's a large nation but it's still weak, still very weak. It needs to get a lot stronger before it can claim a right to a land"
              }
            ]
          },
          {
            "kind": "lineBreak"
          },
          {
            "kind": "lineBreak"
          }
        ]
      },
      {
        "id": "variation_on_tonight_will_be_fine",
        "title": {
          "kind": "text",
          "tokens": [
            {
              "kind": "text",
              "text": "Variation on "
            },
            {
              "kind": "reference",
              "reference": {
                "kind": "document",
                "documentId": "song.tonight_will_be_fine"
              }
            }
          ]
        },
        "fragments": [
          {
            "kind": "text",
            "id": "1",
            "tokens": [
              {
                "kind": "text",
                "text": "(sung as additional verses)"
              }
            ]
          },
          {
            "kind": "lineBreak"
          },
          {
            "kind": "text",
            "id": "2",
            "tokens": [
              {
                "kind": "text",
                "text": " I've looked into the mirrors in numberless places"
              }
            ]
          },
          {
            "kind": "lineBreak"
          },
          {
            "kind": "text",
            "id": "3",
            "tokens": [
              {
                "kind": "text",
                "text": " They all smile back at me with the most troublesome faces."
              }
            ]
          },
          {
            "kind": "lineBreak"
          },
          {
            "kind": "text",
            "id": "4",
            "tokens": [
              {
                "kind": "text",
                "text": " The cards that they dealt me, no there weren't any aces"
              }
            ]
          },
          {
            "kind": "lineBreak"
          },
          {
            "kind": "text",
            "id": "5",
            "tokens": [
              {
                "kind": "text",
                "text": " And the horses just don't listen to me at the races."
              }
            ]
          },
          {
            "kind": "lineBreak"
          },
          {
            "kind": "lineBreak"
          },
          {
            "kind": "text",
            "id": "6",
            "tokens": [
              {
                "kind": "text",
                "text": " There's still one or two of us, walking the street"
              }
            ]
          },
          {
            "kind": "lineBreak"
          },
          {
            "kind": "text",
            "id": "7",
            "tokens": [
              {
                "kind": "text",
                "text": " No arrows of direction painted under our feet"
              }
            ]
          },
          {
            "kind": "lineBreak"
          },
          {
            "kind": "text",
            "id": "8",
            "tokens": [
              {
                "kind": "text",
                "text": " No angels to warn us away from the heat"
              }
            ]
          },
          {
            "kind": "lineBreak"
          },
          {
            "kind": "text",
            "id": "9",
            "tokens": [
              {
                "kind": "text",
                "text": " And no honey to keep us where it is sweet"
              }
            ]
          },
          {
            "kind": "lineBreak"
          },
          {
            "kind": "lineBreak"
          }
        ]
      }
    ]
  }
}