{
  "title": "Heart with No Companion",
  "content": {
    "content": {
      "text": [
        [
          "Now I greet you from the other side of sorrow and despair, with a love so vast",
          "And so shattered, it will reach you everywhere."
        ],
        [
          "And I sing this for the captain whose ship has not been built, for the mother in",
          "Confusion, her cradle still unfilled."
        ],
        [
          "For the heart with no companion, for the soul without a king. for the prima",
          "Ballerina who cannot dance to anything."
        ],
        [
          "Through the days of shame that are coming, through the nights of wild distress,",
          "Though your promise count for nothing, you must keep it nonetheless."
        ],
        [
          "You must keep it for the captain whose ship has not been built. for the mother in",
          "Confusion her cradle still unfilled."
        ],
        [
          "For the heart with no companion, for the soul without a king, for the prima",
          "Ballerina who cannot dance to anything."
        ]
      ]
    }
  },
  "kind": "song",
  "annotations": [
    {
      "anchor": "p1.l0",
      "tokens": [
        {
          "kind": "docref",
          "docRef": "symbol.ship"
        }
      ]
    },
    {
      "anchor": "p1.l0",
      "tokens": [
        {
          "kind": "docref",
          "docRef": "symbol.mother"
        }
      ]
    },
    {
      "anchor": "p2.l0",
      "tokens": [
        {
          "kind": "docref",
          "docRef": "symbol.heart"
        }
      ]
    },
    {
      "anchor": "p2.l1",
      "tokens": [
        {
          "kind": "docref",
          "docRef": "symbol.dance"
        }
      ]
    },
    {
      "anchor": "p3.l0",
      "tokens": [
        {
          "kind": "docref",
          "docRef": "symbol.day"
        }
      ]
    },
    {
      "anchor": "p3.l0",
      "tokens": [
        {
          "kind": "docref",
          "docRef": "symbol.night"
        }
      ]
    },
    {
      "anchor": "p4.l0",
      "tokens": [
        {
          "kind": "docref",
          "docRef": "symbol.ship"
        }
      ]
    },
    {
      "anchor": "p4.l0",
      "tokens": [
        {
          "kind": "docref",
          "docRef": "symbol.mother"
        }
      ]
    },
    {
      "anchor": "p5.l0",
      "tokens": [
        {
          "kind": "docref",
          "docRef": "symbol.heart"
        }
      ]
    },
    {
      "anchor": "p5.l1",
      "tokens": [
        {
          "kind": "docref",
          "docRef": "symbol.dance"
        }
      ]
    }
  ]
}